findiff/__init__.py
findiff/coefs.py
findiff/compatible.py
findiff/grids.py
findiff/operators.py
findiff/pde.py
findiff/stencils.py
findiff/symbolic.py
findiff/utils.py
findiff/vector.py
findiff/legacy/__init__.py
findiff/legacy/operators.py
findiff-0.12.0.dist-info/LICENSE
findiff-0.12.0.dist-info/METADATA
findiff-0.12.0.dist-info/WHEEL
findiff-0.12.0.dist-info/top_level.txt
findiff-0.12.0.dist-info/RECORD
