Metadata-Version: 2.1
Name: findiff
Version: 0.12.0
Summary: A Python package for finite difference derivatives in any number of dimensions.
Author: Matthias Baer
Maintainer-email: Matthias Baer <matthias.r.baer@googlemail.com>
License: MIT
Project-URL: Homepage, https://github.com/maroba/findiff
Project-URL: source, https://github.com/maroba/findiff
Project-URL: Issues, https://github.com/maroba/findiff/issues
Project-URL: tracker, https://github.com/maroba/findiff/issues
Keywords: finite-differences,numerical-derivatives,scientific-computing
Classifier: Programming Language :: Python :: 3
Classifier: Programming Language :: Python :: 3.8
Classifier: Programming Language :: Python :: 3.9
Classifier: Programming Language :: Python :: 3.10
Classifier: Programming Language :: Python :: 3.11
Classifier: Programming Language :: Python :: 3.12
Classifier: Intended Audience :: Developers
Classifier: Topic :: Scientific/Engineering :: Mathematics
Classifier: License :: OSI Approved :: MIT License
Classifier: Operating System :: OS Independent
Requires-Python: >=3.8
License-File: LICENSE
Requires-Dist: numpy
Requires-Dist: scipy
Requires-Dist: sympy
